moleculekit/__init__.py
moleculekit/align.py
moleculekit/atomselect_utils.cpython-311-aarch64-linux-gnu.so
moleculekit/binpos.cpython-311-aarch64-linux-gnu.so
moleculekit/bondguesser.py
moleculekit/bondguesser_utils.cpython-311-aarch64-linux-gnu.so
moleculekit/config.py
moleculekit/cython_utils.cpython-311-aarch64-linux-gnu.so
moleculekit/dcd.cpython-311-aarch64-linux-gnu.so
moleculekit/dihedral.py
moleculekit/distance.py
moleculekit/distance_utils.cpython-311-aarch64-linux-gnu.so
moleculekit/logging.ini
moleculekit/molecule.py
moleculekit/occupancy_utils.cpython-311-aarch64-linux-gnu.so
moleculekit/opm.py
moleculekit/periodictable.py
moleculekit/pymolgraphics.py
moleculekit/rcsb.py
moleculekit/rdkitintegration.py
moleculekit/readers.py
moleculekit/representations.py
moleculekit/residues.py
moleculekit/tmalign.cpython-311-aarch64-linux-gnu.so
moleculekit/trr.cpython-311-aarch64-linux-gnu.so
moleculekit/unitcell.py
moleculekit/util.py
moleculekit/viewer.py
moleculekit/vmd_wrapper
moleculekit/vmdgraphics.py
moleculekit/vmdviewer.py
moleculekit/wrapping.cpython-311-aarch64-linux-gnu.so
moleculekit/writers.py
moleculekit/xtc.cpython-311-aarch64-linux-gnu.so
moleculekit/atomselect/__init__.py
moleculekit/atomselect/analyze.py
moleculekit/atomselect/atomselect.py
moleculekit/atomselect/languageparser.py
moleculekit/fileformats/__init__.py
moleculekit/fileformats/netcdf.py
moleculekit/fileformats/utils.py
moleculekit/interactions/__init__.py
moleculekit/interactions/cationpi.cpython-311-aarch64-linux-gnu.so
moleculekit/interactions/hbonds.cpython-311-aarch64-linux-gnu.so
moleculekit/interactions/interactions.py
moleculekit/interactions/pipi.cpython-311-aarch64-linux-gnu.so
moleculekit/interactions/sigmahole.cpython-311-aarch64-linux-gnu.so
moleculekit/pdbx/__init__.py
moleculekit/pdbx/reader/BinaryCifReader.py
moleculekit/pdbx/reader/PdbxContainers.py
moleculekit/pdbx/reader/PdbxParser.py
moleculekit-1.11.1.dist-info/METADATA
moleculekit-1.11.1.dist-info/WHEEL
moleculekit-1.11.1.dist-info/top_level.txt
moleculekit-1.11.1.dist-info/RECORD
moleculekit-1.11.1.dist-info/licenses/LICENSE
