Metadata-Version: 2.4
Name: moleculekit
Version: 1.11.1
Summary: A molecule reading/writing and manipulation package.
Author-email: Stefan Doerr <s.doerr@acellera.com>
Project-URL: Homepage, https://github.com/Acellera/moleculekit
Project-URL: Bug Tracker, https://github.com/Acellera/moleculekit/issues
Classifier: Programming Language :: Python :: 3
Classifier: Operating System :: POSIX :: Linux
Requires-Python: >=3.9
License-File: LICENSE
Requires-Dist: numpy>=1.23.5
Requires-Dist: pandas>=1.1.2
Requires-Dist: networkx
Requires-Dist: tqdm
Requires-Dist: msgpack
Requires-Dist: requests
Requires-Dist: matplotlib
Requires-Dist: rdkit>=2020.09.5
Requires-Dist: mdtraj
Requires-Dist: propka
Requires-Dist: pdb2pqr>=3.5.3
Requires-Dist: biopython
Dynamic: license-file
